devo_model_manager_client/__init__.py
devo_model_manager_client/api_client.py
devo_model_manager_client/configuration.py
devo_model_manager_client/rest.py
devo_model_manager_client/api/__init__.py
devo_model_manager_client/api/default_api.py
devo_model_manager_client/custom/__init__.py
devo_model_manager_client/custom/api_client_hmac_auth.py
devo_model_manager_client/custom/model_server.py
devo_model_manager_client/models/__init__.py
devo_model_manager_client/models/body.py
devo_model_manager_client/models/body1.py
devo_model_manager_client/models/cluster.py
devo_model_manager_client/models/field.py
devo_model_manager_client/models/image.py
devo_model_manager_client/models/login_response.py
devo_model_manager_client/models/model.py
devo_model_manager_client/models/model_detail.py
devo_model_manager_client/models/model_review.py
devo_model_manager-1.8.6.dist-info/LICENSE
devo_model_manager-1.8.6.dist-info/METADATA
devo_model_manager-1.8.6.dist-info/WHEEL
devo_model_manager-1.8.6.dist-info/top_level.txt
devo_model_manager-1.8.6.dist-info/RECORD
