Metadata-Version: 2.1
Name: devo-model-manager
Version: 1.8.6
Summary: Devo Model Manager API
Home-page: 
Author-email: machine.learning@devo.com
Keywords: Swagger,Devo Model Manager API
License-File: LICENSE
Requires-Dist: urllib3 (>=1.15)
Requires-Dist: six (>=1.10)
Requires-Dist: certifi
Requires-Dist: python-dateutil
